od_import/__init__.py
od_import/hooks.py
od_import/archive_providers/__init__.py
od_import/archive_providers/tar.py
od_import/archive_providers/ziph.py
od_import/protocol_handlers/__init__.py
od_import/protocol_handlers/ftp.py
od_import/protocol_handlers/mem.py
od_import/protocol_handlers/pip_handler.py
od_import/protocol_handlers/smb.py
od_import/protocol_handlers/http/__init__.py
od_import/protocol_handlers/http/_core_python.py
od_import/protocol_handlers/http/_core_winhttp.py
od_import/protocol_handlers/http/directory_of.py
od_import/protocol_handlers/http/dropbox.py
od_import/protocol_handlers/http/git.py
od_import/protocol_handlers/http/git_api.py
od_import/protocol_handlers/http/git_zip.py
od_import/protocol_handlers/http/pastebin.py
od_import/protocol_handlers/http/pypi.py
od_import/protocol_handlers/http/s3.py
od_import/protocol_handlers/http/windows/__init__.py
od_import/protocol_handlers/http/windows/winhttp.py
od_import-0.0.1.dist-info/LICENSE
od_import-0.0.1.dist-info/METADATA
od_import-0.0.1.dist-info/WHEEL
od_import-0.0.1.dist-info/top_level.txt
od_import-0.0.1.dist-info/RECORD
